sarpy/__about__.py
sarpy/__details__.py
sarpy/__init__.py
sarpy/compliance.py
sarpy/annotation/__init__.py
sarpy/annotation/afrl_rde.py
sarpy/annotation/base.py
sarpy/annotation/label.py
sarpy/annotation/rcs.py
sarpy/annotation/afrl_rde_elements/CollectionInfo.py
sarpy/annotation/afrl_rde_elements/FiducialInfo.py
sarpy/annotation/afrl_rde_elements/ImageInfo.py
sarpy/annotation/afrl_rde_elements/ObjectInfo.py
sarpy/annotation/afrl_rde_elements/Research.py
sarpy/annotation/afrl_rde_elements/SensorInfo.py
sarpy/annotation/afrl_rde_elements/SubCollectionInfo.py
sarpy/annotation/afrl_rde_elements/__init__.py
sarpy/annotation/afrl_rde_elements/base.py
sarpy/annotation/afrl_rde_elements/blocks.py
sarpy/annotation/afrl_rde_schema/__init__.py
sarpy/annotation/afrl_rde_schema/afrl_rde_schema_v1.0.0_2022-02-15.xsd
sarpy/consistency/__init__.py
sarpy/consistency/consistency.py
sarpy/consistency/cphd_consistency.py
sarpy/consistency/parsers.py
sarpy/consistency/sicd_consistency.py
sarpy/consistency/sidd_consistency.py
sarpy/geometry/__init__.py
sarpy/geometry/geocoords.py
sarpy/geometry/geometry_elements.py
sarpy/geometry/latlon.py
sarpy/geometry/point_projection.py
sarpy/io/__init__.py
sarpy/io/kml.py
sarpy/io/DEM/DEM.py
sarpy/io/DEM/DTED.py
sarpy/io/DEM/__init__.py
sarpy/io/DEM/geoid.py
sarpy/io/DEM/utils.py
sarpy/io/complex/__init__.py
sarpy/io/complex/aggregate.py
sarpy/io/complex/base.py
sarpy/io/complex/capella.py
sarpy/io/complex/converter.py
sarpy/io/complex/csk.py
sarpy/io/complex/gff.py
sarpy/io/complex/iceye.py
sarpy/io/complex/nisar.py
sarpy/io/complex/other_nitf.py
sarpy/io/complex/palsar2.py
sarpy/io/complex/radarsat.py
sarpy/io/complex/sentinel.py
sarpy/io/complex/sicd.py
sarpy/io/complex/sio.py
sarpy/io/complex/tsx.py
sarpy/io/complex/utils.py
sarpy/io/complex/naming/__init__.py
sarpy/io/complex/naming/utils.py
sarpy/io/complex/sicd_elements/Antenna.py
sarpy/io/complex/sicd_elements/CollectionInfo.py
sarpy/io/complex/sicd_elements/ErrorStatistics.py
sarpy_d-1.3.23.dist-info/LICENSE
sarpy_d-1.3.23.dist-info/METADATA
sarpy_d-1.3.23.dist-info/WHEEL
sarpy_d-1.3.23.dist-info/top_level.txt
sarpy_d-1.3.23.dist-info/RECORD
