Metadata-Version: 2.1
Name: sarpy-d
Version: 1.3.23
Summary: Python tools for reading, writing, and simple processing of complex SAR data and other associated data.
Home-page: https://github.com/davidraleigh/sarpy
Author: National Geospatial-Intelligence Agency
Author-email: Wade.C.Schwartzkopf@nga.mil
License: MIT
Platform: any
Classifier: Development Status :: 4 - Beta
Classifier: Intended Audience :: Developers
Classifier: License :: OSI Approved :: MIT License
Classifier: Programming Language :: Python :: 3
Classifier: Programming Language :: Python :: 3.6
Classifier: Programming Language :: Python :: 3.7
Classifier: Programming Language :: Python :: 3.8
Classifier: Programming Language :: Python :: 3.9
Classifier: Programming Language :: Python :: 3.10
License-File: LICENSE
Requires-Dist: numpy (>=1.11.0)
Requires-Dist: scipy
